biodatatypes/__init__.py
biodatatypes/constants/__init__.py
biodatatypes/constants/aminoacid.py
biodatatypes/constants/codon.py
biodatatypes/constants/nucleotide.py
biodatatypes/sequence/__init__.py
biodatatypes/sequence/types.py
biodatatypes/unit/__init__.py
biodatatypes/unit/base.py
biodatatypes/unit/mixins.py
biodatatypes/unit/types.py
biodatatypes-0.2.1.dist-info/LICENSE
biodatatypes-0.2.1.dist-info/METADATA
biodatatypes-0.2.1.dist-info/WHEEL
biodatatypes-0.2.1.dist-info/top_level.txt
biodatatypes-0.2.1.dist-info/RECORD
