Metadata-Version: 2.1
Name: biodatatypes
Version: 0.2.1
Summary: Nucleotide, amino acid, and codon datatypes for Python
Home-page: https://github.com/kentwait/biodatatypes
Author: Kent Kawashima
Author-email: kentkawashima@gmail.com
License: MIT
Project-URL: Source, https://github.com/kentwait/biodatatypes
Project-URL: Bug Tracker, https://github.com/kentwait/biodatatypes/issues
Keywords: bioinformatics,biology,biological sequence,datatypes
License-File: LICENSE
